mky_utils/__init__.py
mky_utils/package_tracker.py
mky_utils/update_dependencies.py
mky_utils/utils.py
mky_utils-0.2.3.dist-info/METADATA
mky_utils-0.2.3.dist-info/WHEEL
mky_utils-0.2.3.dist-info/top_level.txt
mky_utils-0.2.3.dist-info/RECORD
