Metadata-Version: 2.2
Name: mky_utils
Version: 0.2.3
Summary: A basic utility library
License: MIT
Keywords: utilities,python
Classifier: Programming Language :: Python :: 3
Classifier: License :: OSI Approved :: MIT License
Classifier: Operating System :: OS Independent
Requires-Python: >=3.6
Requires-Dist: requests
Requires-Dist: toml
Requires-Dist: pre-commit
